containers/AVLTree.py
containers/BST.py
containers/BinaryTree.py
containers/Heap.py
containers/fibonacci.py
containers/range.py
containers/unicode.py
cmc_csci046_ds-1.0.0.dist-info/LICENSE
cmc_csci046_ds-1.0.0.dist-info/METADATA
cmc_csci046_ds-1.0.0.dist-info/WHEEL
cmc_csci046_ds-1.0.0.dist-info/top_level.txt
cmc_csci046_ds-1.0.0.dist-info/RECORD
