Metadata-Version: 2.1
Name: cmc-csci046-ds
Version: 1.0.0
Summary: Python implementation of common tree-based data structures.
Home-page: https://github.com/n8stringham/containers-ds
License: BSD3
Platform: UNKNOWN
Classifier: Programming Language :: Python :: 3
Classifier: Programming Language :: Python :: 3.7
Requires-Dist: hypothesis
Requires-Dist: pytest
